sibra_logger/__init__.py
sibra_logger/config.py
sibra_logger/log_config.yaml
sibra_logger/setup.py
tests/__init__.py
tests/test_cleanup.py
tests/test_dynamic_reload.py
tests/test_logging_output.py
tests/test_setup.py
sibra_logger-1.0.0.dist-info/LICENSE
sibra_logger-1.0.0.dist-info/METADATA
sibra_logger-1.0.0.dist-info/WHEEL
sibra_logger-1.0.0.dist-info/top_level.txt
sibra_logger-1.0.0.dist-info/RECORD
