Metadata-Version: 2.1
Name: sibra_logger
Version: 1.0.0
Summary: Configurable logging for Python applications
Home-page: https://github.com/primabonito/sibralogger
Author: Ashraf Inamdar
Author-email: ashrafinamdar@gmail.com
License: MIT
Keywords: logging python configurable logging yaml configuration
Classifier: Programming Language :: Python :: 3
Classifier: Programming Language :: Python :: 3.8
Classifier: License :: OSI Approved :: MIT License
Classifier: Operating System :: OS Independent
Requires-Python: >=3.6
License-File: LICENSE
Requires-Dist: pyyaml>=5.4.1
Provides-Extra: dev
Requires-Dist: pytest>=6.2.5; extra == "dev"
Requires-Dist: pytest-mock>=3.6.1; extra == "dev"
Requires-Dist: twine>=4.0.0; extra == "dev"
